simple_agentcore_runtime_patterns/__init__.py
simple_agentcore_runtime_patterns/py.typed
simple_agentcore_runtime_patterns/_jsii/__init__.py
simple_agentcore_runtime_patterns/_jsii/simple-agentcore-runtime-patterns@0.0.0.jsii.tgz
simple_agentcore_runtime_patterns-0.0.0.dist-info/LICENSE
simple_agentcore_runtime_patterns-0.0.0.dist-info/METADATA
simple_agentcore_runtime_patterns-0.0.0.dist-info/WHEEL
simple_agentcore_runtime_patterns-0.0.0.dist-info/top_level.txt
simple_agentcore_runtime_patterns-0.0.0.dist-info/RECORD
