Metadata-Version: 2.1
Name: simple-agentcore-runtime-patterns
Version: 0.0.0
Summary: AWS CDK construct library for deploying Bedrock AgentCore Runtime
Home-page: https://github.com/ivorycirrus/simple-agentcore-construct.git
Author: @ivorycirrus<ivorycirrus@gmail.com>
License: MIT-0
Project-URL: Source, https://github.com/ivorycirrus/simple-agentcore-construct.git
Classifier: Intended Audience :: Developers
Classifier: Operating System :: OS Independent
Classifier: Programming Language :: JavaScript
Classifier: Programming Language :: Python :: 3 :: Only
Classifier: Programming Language :: Python :: 3.9
Classifier: Programming Language :: Python :: 3.10
Classifier: Programming Language :: Python :: 3.11
Classifier: Typing :: Typed
Classifier: Development Status :: 5 - Production/Stable
Classifier: License :: OSI Approved
Requires-Python: ~=3.9
License-File: LICENSE
Requires-Dist: aws-cdk-lib <3.0.0,>=2.221.0
Requires-Dist: cdk-ecr-deployment <5.0.0,>=4.0.3
Requires-Dist: cdk-nag <3.0.0,>=2.37.55
Requires-Dist: constructs <11.0.0,>=10.0.5
Requires-Dist: jsii <2.0.0,>=1.118.0
Requires-Dist: publication >=0.0.3
Requires-Dist: typeguard <4.3.0,>=2.13.3
